application_model/__init__.py
application_model/application_model.py
application_model/data_processing/__init__.py
application_model/data_processing/category_encoder.py
application_model/data_processing/data_processor.py
application_model/data_processing/numeric_standardizer.py
application_model/featurization/__init__.py
application_model/featurization/new_features.py
application_model/resources/__init__.py
application_model/resources/data.json
application_model/resources/data_processor.pkl
application_model/resources/model.pkl
application_model/utils/constants.py
application_model-0.6.0.dist-info/LICENSE
application_model-0.6.0.dist-info/METADATA
application_model-0.6.0.dist-info/WHEEL
application_model-0.6.0.dist-info/RECORD
