Metadata-Version: 2.1
Name: application_model
Version: 0.6.0
Summary: Generate application score for new customers.
License: Proprietary
Author: Wesllen Sousa Lima
Requires-Python: >=3.9,<4.0
Classifier: License :: Other/Proprietary License
Classifier: Programming Language :: Python :: 3
Classifier: Programming Language :: Python :: 3.9
Classifier: Programming Language :: Python :: 3.10
Classifier: Programming Language :: Python :: 3.11
Classifier: Programming Language :: Python :: 3.12
Requires-Dist: numpy (>=1.26.4,<2.0.0)
Requires-Dist: pandas (==1.3.5)
Requires-Dist: scikit-learn (==1.3.2)
